{
  "Dependencies": [
    "SMLHelper"
  ],
  "Id": "BrineSuit",
  "VersionChecker": {
    "LatestVersionUrl": "https://raw.githubusercontent.com/DaWrecka/DaWreckasSubnauticaStuff/master/AcidProofSuit/mod.json"
  },
  "Enable": true,
  "VersionDependencies": {
    "SMLHelper": "2.9"
  },
  "Game": "Subnautica",
  "AssemblyName": "BrineSuit.dll",
  "Author": "DaWrecka w/ MrPurple6411",
  "Version": "1.2.0.3",
  "DisplayName": "Brine Suit",
  "NexusId": {
    "Subnautica": "597"
  },
  "LoadAfter": [
    "NitrogenMod"
  ]
}
